{
  "i": "challenge-0003",
  "n": "00000000-0000-0000-0000-000000000000",
  "rs": [
    "requested_scope-0003_1"
  ],
  "ls": true,
  "s": "subject-0003",
  "oc": {
    "display": "display-0003"
  },
  "r": "http://request/0003",
  "si": "auth_session-0003",
  "lv": "verifier-0003",
  "lc": "csrf-0003",
  "li": null,
  "ia": "0001-01-01T00:00:00Z",
  "q": 128,
  "lr": true,
  "lf": 3,
  "a": "acr-0003",
  "fs": "force_subject_id-0003",
  "ct": {},
  "lu": true,
  "le": {
    "error": "",
    "error_description": "",
    "error_hint": "",
    "status_code": 0,
    "error_debug": "",
    "valid": false
  },
  "la": null,
  "cc": "challenge-0003",
  "cs": true,
  "cv": "verifier-0003",
  "cr": "csrf-0003",
  "gs": [
    "granted_scope-0003_1"
  ],
  "ce": true,
  "cf": 3,
  "ch": null,
  "cw": true,
  "cx": {
    "error": "",
    "error_description": "",
    "error_hint": "",
    "status_code": 0,
    "error_debug": "",
    "valid": false
  },
  "st": {
    "session_id_token-0003": "0003"
  },
  "sa": {
    "session_access_token-0003": "0003"
  }
}
